Workbook

Sheet Cover
B2: CloudRobotics Co.
B3: Historical Financial Statements
B4: Prepared for ECRA System Ingestion
B6: Sheet | C6: Contents | D6: Period
B7: P&L Statement | C7: Revenue, Gross Profit, EBITDA, Net Profit | D7: FY2023–FY2026 Actuals + FY2027E
B8: Balance Sheet | C8: Assets, Liabilities, Equity, Balance Check | D8: FY2023–FY2026 Actuals + FY2027E
B9: Cash Flow Statement | C9: Operating, Investing, Financing, Closing Cash | D9: FY2023–FY2026 Actuals + FY2027E
B10: Assumptions & Ratios | C10: Key drivers, Liquidity, Profitability, Leverage | D10: FY2023–FY2026 Actuals + FY2027E
B12: Colour Convention
B13: Blue text — Hardcoded inputs (change for scenarios)
B14: Black text — Formulas & calculations
B15: Green text — Cross-sheet links
B17: Note: All figures in INR Lakhs. FY = April–March (Indian fiscal year). FY2023 = pre-incorporation bootstrap. FY2025 unaudited — management accounts. FY2026 and FY2027E are projections. Data is illustrative for ECRA ingestion.

Sheet P&L Statement
A1: CloudRobotics Co. — Profit & Loss Statement
A2: All figures in INR Lakhs | FY ending 31 March | Illustrative — for ECRA ingestion
B4: Note | C4: FY2023 | D4: FY2024 | E4: FY2025 | F4: FY2026 (Unaudited) | G4: FY2027E
A5: REVENUE
A6: Hardware Sales | B6: R1 | F6: 180 | G6: 540
A7: RaaS Subscriptions | B7: R2 | F7: 50 | G7: 520
A8: Cloud Platform License | B8: R3 | F8: 20 | G8: 140
A9: Grant / Pilot Revenue | B9: R4 | E9: 15
A10: Total Revenue | C10: =SUM(C6:C9) -> 0 | D10: =SUM(D6:D9) -> 0 | E10: =SUM(E6:E9) -> 15 | F10: =SUM(F6:F9) -> 250 | G10: =SUM(G6:G9) -> 1200
A12: COST OF GOODS SOLD (COGS)
A13: Hardware — BOM & Contract Manufacturing | E13: 10 | F13: 117 | G13: 351
A14: Hardware — Logistics & Warranty | E14: 2 | F14: 18 | G14: 54
A15: Cloud Infrastructure Costs | E15: 3 | F15: 20 | G15: 80
A16: Total COGS | C16: =SUM(C13:C15) -> 0 | D16: =SUM(D13:D15) -> 0 | E16: =SUM(E13:E15) -> 15 | F16: =SUM(F13:F15) -> 155 | G16: =SUM(G13:G15) -> 485
A17: Gross Profit | C17: =C10-C16 -> 0 | D17: =D10-D16 -> 0 | E17: =E10-E16 -> 0 | F17: =F10-F16 -> 95 | G17: =G10-G16 -> 715
A18: Gross Margin % | C18: =IF(C10=0,"-",C17/C10) -> - | D18: =IF(D10=0,"-",D17/D10) -> - | E18: =IF(E10=0,"-",E17/E10) -> 0 | F18: =IF(F10=0,"-",F17/F10) -> 0.38 | G18: =IF(G10=0,"-",G17/G10) -> 0.59583333
A20: OPERATING EXPENSES
A21: R&D & Product Engineering | C21: 8 | D21: 35 | E21: 120 | F21: 550 | G21: 700
A22: Salaries — Non-Engineering | C22: 5 | D22: 12 | E22: 45 | F22: 80 | G22: 200
A23: Sales & Marketing | D23: 3 | E23: 10 | F23: 150 | G23: 350
A24: General & Administrative | C24: 3 | D24: 8 | E24: 25 | F24: 100 | G24: 150
A25: Rent & Facilities | C25: 2 | D25: 4 | E25: 12 | F25: 24 | G25: 36
A26: Depreciation & Amortisation | C26: 1 | D26: 4 | E26: 10 | F26: 40 | G26: 60
A27: Legal, Compliance & IP | C27: 2 | D27: 6 | E27: 18 | F27: 30 | G27: 40
A28: Travel & Business Development | C28: 1 | D28: 2 | E28: 8 | F28: 20 | G28: 40
A29: Total Operating Expenses | C29: =SUM(C21:C28) -> 22 | D29: =SUM(D21:D28) -> 74 | E29: =SUM(E21:E28) -> 248 | F29: =SUM(F21:F28) -> 994 | G29: =SUM(G21:G28) -> 1576
A31: EBITDA | C31: =C17-C29 -> -22 | D31: =D17-D29 -> -74 | E31: =E17-E29 -> -248 | F31: =F17-F29 -> -899 | G31: =G17-G29 -> -861
A32: EBITDA Margin % | C32: =IF(C10=0,"-",C31/C10) -> - | D32: =IF(D10=0,"-",D31/D10) -> - | E32: =IF(E10=0,"-",E31/E10) -> -16.533333 | F32: =IF(F10=0,"-",F31/F10) -> -3.596 | G32: =IF(G10=0,"-",G31/G10) -> -0.7175
A33: Finance Income / (Cost) | D33: 1 | E33: 4 | F33: 20 | G33: 15
A34: Net Profit / (Loss) Before Tax | C34: =C31+C33 -> -22 | D34: =D31+D33 -> -73 | E34: =E31+E33 -> -244 | F34: =F31+F33 -> -879 | G34: =G31+G33 -> -846
A35: Income Tax Expense | C35: =IF(C34>0,C34*0.25,0) -> 0 | D35: =IF(D34>0,D34*0.25,0) -> 0 | E35: =IF(E34>0,E34*0.25,0) -> 0 | F35: =IF(F34>0,F34*0.25,0) -> 0 | G35: =IF(G34>0,G34*0.25,0) -> 0
A36: Net Profit / (Loss) After Tax | C36: =C34-C35 -> -22 | D36: =D34-D35 -> -73 | E36: =E34-E35 -> -244 | F36: =F34-F35 -> -879 | G36: =G34-G35 -> -846
A37: Net Margin % | C37: =IF(C10=0,"-",C36/C10) -> - | D37: =IF(D10=0,"-",D36/D10) -> - | E37: =IF(E10=0,"-",E36/E10) -> -16.266667 | F37: =IF(F10=0,"-",F36/F10) -> -3.516 | G37: =IF(G10=0,"-",G36/G10) -> -0.705
A39: Source: CloudRobotics Co. internal management accounts. FY2023 = pre-incorporation bootstrap phase. FY2024 = first full operating year. FY2025 = post-seed deployment. FY2026 = actuals (unaudited, FY ended 31 Mar 2026). FY2027E = current-year projection. All figures INR Lakhs. Audit not yet completed for FY2025 — unaudited management accounts.
A40: Colour convention: Blue = hardcoded input | Black = formula | Green = cross-sheet link

Sheet Balance Sheet
A1: CloudRobotics Co. — Balance Sheet
A2: All figures in INR Lakhs | As at 31 March | Illustrative — for ECRA ingestion
B4: Note | C4: FY2023 | D4: FY2024 | E4: FY2025 | F4: FY2026 (Unaudited) | G4: FY2027E
A5: NON-CURRENT ASSETS
A6: Property, Plant & Equipment (net) | D6: 5 | E6: 28 | F6: 55 | G6: 120
A7: Intangible Assets (IP & Software) | D7: 8 | E7: 22 | F7: 40 | G7: 60
A8: Security Deposits | C8: 1 | D8: 1 | E8: 3 | F8: 5 | G8: 8
A9: Right-of-Use Assets | D9: 3 | E9: 8 | F9: 12 | G9: 20
A10: Total Non-Current Assets | C10: =SUM(C6:C9) -> 1 | D10: =SUM(D6:D9) -> 17 | E10: =SUM(E6:E9) -> 61 | F10: =SUM(F6:F9) -> 112 | G10: =SUM(G6:G9) -> 208
A12: CURRENT ASSETS
A13: Cash & Cash Equivalents | C13: 5 | D13: 20 | E13: 290 | F13: 2420 | G13: 3570
A14: Trade Receivables | D14: 2 | E14: 12 | F14: 45 | G14: 180
A15: Inventory (robot components & WIP) | D15: 10 | E15: 30 | F15: 80 | G15: 200
A16: Prepaid Expenses & Other | C16: 1 | D16: 2 | E16: 5 | F16: 12 | G16: 25
A17: GST Receivable / Input Tax Credit | D17: 3 | E17: 8 | F17: 20 | G17: 50
A18: Total Current Assets | C18: =SUM(C13:C17) -> 6 | D18: =SUM(D13:D17) -> 37 | E18: =SUM(E13:E17) -> 345 | F18: =SUM(F13:F17) -> 2577 | G18: =SUM(G13:G17) -> 4025
A20: TOTAL ASSETS | C20: =C10+C18 -> 7 | D20: =D10+D18 -> 54 | E20: =E10+E18 -> 406 | F20: =F10+F18 -> 2689 | G20: =G10+G18 -> 4233
A22: EQUITY
A23: Share Capital | C23: 5 | D23: 5 | E23: 5 | F23: 5 | G23: 5
A24: Securities Premium (Seed + Series A) | D24: 40 | E24: 305 | F24: 305 | G24: 3305
A25: Retained Earnings / (Accumulated Loss) | D25: -22 | E25: -195 | F25: -935 | G25: -1735
A26: Total Equity | C26: =SUM(C23:C25) -> 5 | D26: =SUM(D23:D25) -> 23 | E26: =SUM(E23:E25) -> 115 | F26: =SUM(F23:F25) -> -625 | G26: =SUM(G23:G25) -> 1575
A28: NON-CURRENT LIABILITIES
A29: Lease Liability (Long-term) | D29: 2 | E29: 6 | F29: 9 | G29: 15
A30: Deferred Tax Liability
A31: Total Non-Current Liabilities | C31: =SUM(C29:C30) -> 0 | D31: =SUM(D29:D30) -> 2 | E31: =SUM(E29:E30) -> 6 | F31: =SUM(F29:F30) -> 9 | G31: =SUM(G29:G30) -> 15
A33: CURRENT LIABILITIES
A34: Trade Payables | D34: 4 | E34: 12 | F34: 30 | G34: 80
A35: Employee Dues & Accruals | C35: 1 | D35: 3 | E35: 10 | F35: 25 | G35: 70
A36: GST & Tax Payable | D36: 1 | E36: 3 | F36: 8 | G36: 20
A37: Advance from Customers | E37: 5 | F37: 15 | G37: 35
A38: Lease Liability (Current) | D38: 1 | E38: 2 | F38: 3 | G38: 5
A39: Other Current Liabilities | D39: 2 | E39: 5 | F39: 10 | G39: 20
A40: Total Current Liabilities | C40: =SUM(C34:C39) -> 1 | D40: =SUM(D34:D39) -> 11 | E40: =SUM(E34:E39) -> 37 | F40: =SUM(F34:F39) -> 91 | G40: =SUM(G34:G39) -> 230
A42: TOTAL EQUITY & LIABILITIES | C42: =C26+C31+C40 -> 6 | D42: =D26+D31+D40 -> 36 | E42: =E26+E31+E40 -> 158 | F42: =F26+F31+F40 -> -525 | G42: =G26+G31+G40 -> 1820
A44: BALANCE CHECK (Assets = Equity + Liabilities) | C44: =IF(ABS(C20-C42)<1,"✓ Balanced","✗ CHECK") -> ✗ CHECK | D44: =IF(ABS(D20-D42)<1,"✓ Balanced","✗ CHECK") -> ✗ CHECK | E44: =IF(ABS(E20-E42)<1,"✓ Balanced","✗ CHECK") -> ✗ CHECK | F44: =IF(ABS(F20-F42)<1,"✓ Balanced","✗ CHECK") -> ✗ CHECK | G44: =IF(ABS(G20-G42)<1,"✓ Balanced","✗ CHECK") -> ✗ CHECK
A46: Source: CloudRobotics Co. management accounts. FY2025 unaudited. Cash balance FY2025 includes INR 3.5 Cr (350 Lakhs) seed proceeds received in Q2 FY2025 less cumulative spend to date.
A47: Colour convention: Blue = hardcoded input | Black = formula | Green = cross-sheet link

Sheet Cash Flow Statement
A1: CloudRobotics Co. — Cash Flow Statement
A2: All figures in INR Lakhs | FY ending 31 March | Illustrative — for ECRA ingestion
B4: Note | C4: FY2023 | D4: FY2024 | E4: FY2025 | F4: FY2026 (Unaudited) | G4: FY2027E
A5: A. CASH FLOWS FROM OPERATING ACTIVITIES
A6: Net Profit / (Loss) After Tax (from P&L) | C6: ='P&L Statement'!C36 -> -22 | D6: ='P&L Statement'!D36 -> -73 | E6: ='P&L Statement'!E36 -> -244 | F6: ='P&L Statement'!F36 -> -879 | G6: ='P&L Statement'!G36 -> -846
A7: Add: Depreciation & Amortisation | C7: 1 | D7: 4 | E7: 10 | F7: 40 | G7: 60
A8: (Increase) / Decrease in Trade Receivables | D8: -2 | E8: -10 | F8: -33 | G8: -168
A9: (Increase) / Decrease in Inventory | D9: -10 | E9: -20 | F9: -50 | G9: -120
A10: (Increase) / Decrease in Prepaid & Other | C10: -1 | D10: -1 | E10: -3 | F10: -7 | G10: -13
A11: Increase / (Decrease) in Trade Payables | D11: 4 | E11: 8 | F11: 18 | G11: 68
A12: Increase / (Decrease) in Employee Dues | C12: 1 | D12: 2 | E12: 7 | F12: 15 | G12: 45
A13: Increase / (Decrease) in Other Liabilities | D13: 3 | E13: 7 | F13: 13 | G13: 30
A14: Net Cash from Operating Activities | C14: =SUM(C6:C13) -> -21 | D14: =SUM(D6:D13) -> -73 | E14: =SUM(E6:E13) -> -245 | F14: =SUM(F6:F13) -> -883 | G14: =SUM(G6:G13) -> -944
A16: B. CASH FLOWS FROM INVESTING ACTIVITIES
A17: Purchase of Property, Plant & Equipment | D17: -6 | E17: -25 | F17: -45 | G17: -100
A18: Development of Intangible Assets / IP | D18: -9 | E18: -20 | F18: -30 | G18: -40
A19: Security Deposits Paid | C19: -1 | D19: -1 | E19: -2 | F19: -2 | G19: -3
A20: Net Cash from Investing Activities | C20: =SUM(C17:C19) -> -1 | D20: =SUM(D17:D19) -> -16 | E20: =SUM(E17:E19) -> -47 | F20: =SUM(F17:F19) -> -77 | G20: =SUM(G17:G19) -> -143
A22: C. CASH FLOWS FROM FINANCING ACTIVITIES
A23: Proceeds from Share Issuance (Seed / Series A) | C23: 5 | D23: 45 | E23: 305 | G23: 3000
A24: Repayment of Lease Liabilities | D24: -1 | E24: -2 | F24: -3 | G24: -5
A25: Founders' Capital Contribution | C25: 5
A26: Net Cash from Financing Activities | C26: =SUM(C23:C25) -> 10 | D26: =SUM(D23:D25) -> 44 | E26: =SUM(E23:E25) -> 303 | F26: =SUM(F23:F25) -> -3 | G26: =SUM(G23:G25) -> 2995
A28: Net Increase / (Decrease) in Cash | C28: =C14+C20+C26 -> -12 | D28: =D14+D20+D26 -> -45 | E28: =E14+E20+E26 -> 11 | F28: =F14+F20+F26 -> -963 | G28: =G14+G20+G26 -> 1908
A29: Opening Cash & Cash Equivalents | D29: 5 | E29: 20 | F29: 290 | G29: 2420
A30: Closing Cash & Cash Equivalents | C30: =C29+C28 -> -12 | D30: =D29+D28 -> -40 | E30: =E29+E28 -> 31 | F30: =F29+F28 -> -673 | G30: =G29+G28 -> 4328
A32: Cross-Check: Closing Cash = Balance Sheet Cash? | C32: =IF(ABS(C30-'Balance Sheet'!C13)<1,"✓ Match","✗ CHECK") -> ✗ CHECK | D32: =IF(ABS(D30-'Balance Sheet'!D13)<1,"✓ Match","✗ CHECK") -> ✗ CHECK | E32: =IF(ABS(E30-'Balance Sheet'!E13)<1,"✓ Match","✗ CHECK") -> ✗ CHECK | F32: =IF(ABS(F30-'Balance Sheet'!F13)<1,"✓ Match","✗ CHECK") -> ✗ CHECK | G32: =IF(ABS(G30-'Balance Sheet'!G13)<1,"✓ Match","✗ CHECK") -> ✗ CHECK
A34: Source: CloudRobotics Co. management accounts. FY2023 = bootstrap. FY2024 = pre-seed ops. FY2025 = includes INR 305 Lakh seed proceeds (INR 3.5 Cr). FY2026 = actuals (unaudited, FY ended 31 Mar 2026). FY2027E = current-year projection.
A35: Colour convention: Blue = hardcoded input | Black = formula | Green = cross-sheet link (P&L / BS)

Sheet Assumptions & Ratios
A1: CloudRobotics Co. — Key Assumptions & Financial Ratios
C3: FY2023 | D3: FY2024 | E3: FY2025 | F3: FY2026E | G3: FY2027E
A4: OPERATING ASSUMPTIONS | F4: FY2026 (Unaudited) | G4: FY2027E
A5: Robots Deployed (cumulative) | C5: 0 | D5: 0 | E5: 3 | F5: 15 | G5: 75
A6: New Customers (annual) | C6: 0 | D6: 0 | E6: 1 | F6: 2 | G6: 8
A7: Avg Robots per Customer | C7: 0 | D7: 0 | E7: 3 | F7: 7 | G7: 8
A8: RaaS Adoption Rate | F8: 0.3 | G8: 0.55
A9: Hardware ASP (INR Lakhs) | F9: 16 | G9: 17
A10: RaaS ARPU (INR Lakhs/robot/mo) | F10: 1.6 | G10: 1.7
A11: Headcount (FTEs) | C11: 2 | D11: 4 | E11: 12 | F11: 45 | G11: 95
A14: LIQUIDITY RATIOS
A15: Current Ratio (Current Assets / Current Liabilities) | C15: =IF('Balance Sheet'!C40=0,"-",'Balance Sheet'!C18/'Balance Sheet'!C40) -> 6 | D15: =IF('Balance Sheet'!D40=0,"-",'Balance Sheet'!D18/'Balance Sheet'!D40) -> 3.3636364 | E15: =IF('Balance Sheet'!E40=0,"-",'Balance Sheet'!E18/'Balance Sheet'!E40) -> 9.3243243 | F15: =IF('Balance Sheet'!F40=0,"-",'Balance Sheet'!F18/'Balance Sheet'!F40) -> 28.318681 | G15: =IF('Balance Sheet'!G40=0,"-",'Balance Sheet'!G18/'Balance Sheet'!G40) -> 17.5
A16: Cash & Equivalents (INR Lakhs) | C16: ='Balance Sheet'!C13 -> 5 | D16: ='Balance Sheet'!D13 -> 20 | E16: ='Balance Sheet'!E13 -> 290 | F16: ='Balance Sheet'!F13 -> 2420 | G16: ='Balance Sheet'!G13 -> 3570
A17: Cash Runway (months at current burn) | C17: =IF('P&L Statement'!C31>=0,"-",ABS('Balance Sheet'!C13/('P&L Statement'!C31/12))) -> 2.7272727 | D17: =IF('P&L Statement'!D31>=0,"-",ABS('Balance Sheet'!D13/('P&L Statement'!D31/12))) -> 3.2432432 | E17: =IF('P&L Statement'!E31>=0,"-",ABS('Balance Sheet'!E13/('P&L Statement'!E31/12))) -> 14.032258 | F17: =IF('P&L Statement'!F31>=0,"-",ABS('Balance Sheet'!F13/('P&L Statement'!F31/12))) -> 32.302558 | G17: =IF('P&L Statement'!G31>=0,"-",ABS('Balance Sheet'!G13/('P&L Statement'!G31/12))) -> 49.756098
A19: PROFITABILITY RATIOS
A20: Gross Margin % | C20: ='P&L Statement'!C18 -> - | D20: ='P&L Statement'!D18 -> - | E20: ='P&L Statement'!E18 -> 0 | F20: ='P&L Statement'!F18 -> 0.38 | G20: ='P&L Statement'!G18 -> 0.59583333
A21: EBITDA Margin % | C21: ='P&L Statement'!C32 -> - | D21: ='P&L Statement'!D32 -> - | E21: ='P&L Statement'!E32 -> -16.533333 | F21: ='P&L Statement'!F32 -> -3.596 | G21: ='P&L Statement'!G32 -> -0.7175
A22: Net Margin % | C22: ='P&L Statement'!C37 -> - | D22: ='P&L Statement'!D37 -> - | E22: ='P&L Statement'!E37 -> -16.266667 | F22: ='P&L Statement'!F37 -> -3.516 | G22: ='P&L Statement'!G37 -> -0.705
A24: LEVERAGE & COVERAGE
A25: Debt / Equity Ratio | C25: =IF('Balance Sheet'!C26=0,"-",('Balance Sheet'!C31+'Balance Sheet'!C40)/'Balance Sheet'!C26) -> 0.2 | D25: =IF('Balance Sheet'!D26=0,"-",('Balance Sheet'!D31+'Balance Sheet'!D40)/'Balance Sheet'!D26) -> 0.56521739 | E25: =IF('Balance Sheet'!E26=0,"-",('Balance Sheet'!E31+'Balance Sheet'!E40)/'Balance Sheet'!E26) -> 0.37391304 | F25: =IF('Balance Sheet'!F26=0,"-",('Balance Sheet'!F31+'Balance Sheet'!F40)/'Balance Sheet'!F26) -> -0.16 | G25: =IF('Balance Sheet'!G26=0,"-",('Balance Sheet'!G31+'Balance Sheet'!G40)/'Balance Sheet'!G26) -> 0.15555556
A26: Interest Coverage Ratio (EBITDA / Finance Cost) | C26: =IF('P&L Statement'!C33=0,"-",'P&L Statement'!C31/'P&L Statement'!C33) -> - | D26: =IF('P&L Statement'!D33=0,"-",'P&L Statement'!D31/'P&L Statement'!D33) -> -74 | E26: =IF('P&L Statement'!E33=0,"-",'P&L Statement'!E31/'P&L Statement'!E33) -> -62 | F26: =IF('P&L Statement'!F33=0,"-",'P&L Statement'!F31/'P&L Statement'!F33) -> -44.95 | G26: =IF('P&L Statement'!G33=0,"-",'P&L Statement'!G31/'P&L Statement'!G33) -> -57.4
A28: All ratios pull live from P&L Statement and Balance Sheet tabs via green cross-sheet links.
A29: Colour convention: Blue = hardcoded input | Black = formula | Green = cross-sheet link
